sh.py
sh-2.2.0.dist-info/LICENSE.txt
sh-2.2.0.dist-info/METADATA
sh-2.2.0.dist-info/WHEEL
sh-2.2.0.dist-info/RECORD
