Metadata-Version: 2.3
Name: sh
Version: 2.2.0
Summary: Python subprocess replacement
Home-page: https://sh.readthedocs.io/
License: MIT
Author: Andrew Moffat
Author-email: arwmoffat@gmail.com
Maintainer: Andrew Moffat
Maintainer-email: arwmoffat@gmail.com
Requires-Python: >=3.8.1,<4.0
Classifier: Development Status :: 5 - Production/Stable
Classifier: Environment :: Console
Classifier: Intended Audience :: Developers
Classifier: Intended Audience :: System Administrators
Classifier: License :: OSI Approved :: MIT License
Classifier: Programming Language :: Python
Classifier: Programming Language :: Python :: 3
Classifier: Programming Language :: Python :: 3.9
Classifier: Programming Language :: Python :: 3.10
Classifier: Programming Language :: Python :: 3.11
Classifier: Programming Language :: Python :: 3.12
Classifier: Programming Language :: Python :: 3.13
Classifier: Programming Language :: Python :: 3.8
Classifier: Programming Language :: Python :: Implementation :: CPython
Classifier: Programming Language :: Python :: Implementation :: PyPy
Classifier: Topic :: Software Development :: Build Tools
Classifier: Topic :: Software Development :: Libraries :: Python Modules
Project-URL: Documentation, https://sh.readthedocs.io/
Project-URL: Repository, https://github.com/amoffat/sh
